filecloudapi/__init__.py
filecloudapi/__main__.py
filecloudapi/cli.py
filecloudapi/datastructures.py
filecloudapi/exceptions.py
filecloudapi/fcserver.py
filecloudapi/tests/__init__.py
filecloudapi/tests/conftest.py
filecloudapi/tests/test_fcserver.py
filecloudapi_python-0.4.4.dist-info/LICENSE.md
filecloudapi_python-0.4.4.dist-info/METADATA
filecloudapi_python-0.4.4.dist-info/WHEEL
filecloudapi_python-0.4.4.dist-info/RECORD
