Metadata-Version: 2.3
Name: filecloudapi-python
Version: 0.4.4
Summary: A Python library to connect to a Filecloud server
License: Apache-2.0
Author: FileCloud
Author-email: dev@filecloud.com
Requires-Python: >=3.11,<4.0
Classifier: Development Status :: 4 - Beta
Classifier: License :: OSI Approved :: Apache Software License
Classifier: Natural Language :: English
Classifier: Operating System :: OS Independent
Classifier: Programming Language :: Python
Classifier: Programming Language :: Python :: 3
Classifier: Programming Language :: Python :: 3.11
Classifier: Programming Language :: Python :: 3.12
Classifier: Programming Language :: Python :: 3.13
Requires-Dist: click
Requires-Dist: requests
Project-URL: Documentation, https://filecloudapi-python.readthedocs.io
Project-URL: Homepage, https://pypi.org/project/filecloudapi-python
Project-URL: Repository, https://github.com/codelathe/filecloudapi-python
